Metadata-Version: 2.1
Name: bsrag_unstructured
Version: 0.3.8.0
Summary: A Python package with a built-in web application
Author: Dataelement
Author-email: hanfeng@dataelem.com
Requires-Python: >=3.8,<4.0
Classifier: Programming Language :: Python :: 3
Classifier: Programming Language :: Python :: 3.8
Classifier: Programming Language :: Python :: 3.9
Classifier: Programming Language :: Python :: 3.10
Classifier: Programming Language :: Python :: 3.11
Classifier: Programming Language :: Python :: 3.12
Classifier: Programming Language :: Python :: 3.13
Requires-Dist: beautifulsoup4 (>=4.12.2,<4.13.0)
Requires-Dist: certifi (>=2023.7.22,<2023.8.0)
Requires-Dist: cffi (>=1.15.1,<1.16.0)
Requires-Dist: chardet (>=5.1.0,<5.2.0)
Requires-Dist: charset-normalizer (>=3.2.0,<3.3.0)
Requires-Dist: contourpy (>=1.1.0,<1.2.0)
Requires-Dist: cryptography (>=41.0.3,<41.1.0)
Requires-Dist: cycler (>=0.11.0,<0.12.0)
Requires-Dist: ebooklib (>=0.18,<0.19)
Requires-Dist: emoji (>=2.8.0,<2.9.0)
Requires-Dist: et-xmlfile (>=1.1.0,<1.2.0)
Requires-Dist: fastapi (>=0.115.8,<0.116.0)
Requires-Dist: filetype (>=1.2.0,<1.3.0)
Requires-Dist: fonttools (>=4.42.1,<4.43.0)
Requires-Dist: idna (>=3.4,<3.5)
Requires-Dist: importlib-metadata (>=6.8.0,<6.9.0)
Requires-Dist: langdetect (>=1.0.9,<1.1.0)
Requires-Dist: loguru (>=0.7.1,<0.8.0)
Requires-Dist: lxml (>=4.9.3,<4.10.0)
Requires-Dist: markdown (>=3.4.4,<3.5.0)
Requires-Dist: msg-parser (>=1.2.0,<1.3.0)
Requires-Dist: nltk (>=3.8.1,<3.9.0)
Requires-Dist: numpy (>=1.24.4,<1.25.0)
Requires-Dist: olefile (>=0.46,<0.47)
Requires-Dist: opencv-python (>=4.8.0.76,<4.9.0.0)
Requires-Dist: openpyxl (>=3.1.2,<3.2.0)
Requires-Dist: orjson (>=3.10.15,<3.11.0)
Requires-Dist: pandas (>=2.0.3,<2.1.0)
Requires-Dist: pdf2image (>=1.16.3,<1.17.0)
Requires-Dist: pdfminer-six (>=20221105,<20221106)
Requires-Dist: pdfplumber (>=0.10.2,<0.11.0)
Requires-Dist: pillow (>=10.0.0,<10.1.0)
Requires-Dist: pydantic (>=1.10.12,<1.11.0)
Requires-Dist: pymupdf (>=1.23.8,<1.24.0)
Requires-Dist: pypandoc (>=1.11,<1.12)
Requires-Dist: pypdf (>=4.3.0,<4.4.0)
Requires-Dist: python-dateutil (>=2.8.2,<2.9.0)
Requires-Dist: python-docx (>=0.8.11,<0.9.0)
Requires-Dist: python-magic (>=0.4.27,<0.5.0)
Requires-Dist: python-pptx (>=0.6.21,<0.7.0)
Requires-Dist: pytz (>=2023.3,<2023.4)
Requires-Dist: pyyaml (>=6.0.2,<6.1.0)
Requires-Dist: requests (>=2.31.0,<2.32.0)
Requires-Dist: rich (>=13.4.2,<13.5.0)
Requires-Dist: shapely (>=2.0.1,<2.1.0)
Requires-Dist: six (>=1.16.0,<1.17.0)
Requires-Dist: tabulate (>=0.9.0,<0.10.0)
Requires-Dist: transformers (<=4.47.0)
Requires-Dist: tritonclient[http] (==2.41.0)
Requires-Dist: types-pyyaml (>=6.0.12.8,<6.1.0.0)
Requires-Dist: tzdata (>=2023.3,<2023.4)
Requires-Dist: urllib3 (>=1.26.16,<1.27.0)
Requires-Dist: wheel (>=0.41.0,<0.42.0)
Requires-Dist: xlrd (>=2.0.1,<2.1.0)
Requires-Dist: xlsxwriter (>=3.1.2,<3.2.0)
Requires-Dist: zipp (>=3.16.2,<3.17.0)
